LICENSE
MANIFEST.in
README.md
setup.cfg
setup.py
test.py
salesforce_bulkipy/__init__.py
salesforce_bulkipy/bulk_states.py
salesforce_bulkipy/csv_adapter.py
salesforce_bulkipy/salesforce_bulkipy.py
salesforce_bulkipy.egg-info/PKG-INFO
salesforce_bulkipy.egg-info/SOURCES.txt
salesforce_bulkipy.egg-info/dependency_links.txt
salesforce_bulkipy.egg-info/not-zip-safe
salesforce_bulkipy.egg-info/requires.txt
salesforce_bulkipy.egg-info/top_level.txt