Metadata-Version: 1.1
Name: salesforce-bulkipy
Version: 1.0
Summary: A Python library for the Salesforce Bulk API
Home-page: https://github.com/wingify/salesforce-bulkipy
Author: Shreyans Sheth
Author-email: dev.shreyans96@gmail.com
License: Copyright (c) 2016 Shreyans Sheth
